fnordstalk.py
setup.py
stalk.py
fnordstalk.egg-info/PKG-INFO
fnordstalk.egg-info/SOURCES.txt
fnordstalk.egg-info/dependency_links.txt
fnordstalk.egg-info/entry_points.txt
fnordstalk.egg-info/requires.txt
fnordstalk.egg-info/top_level.txt