Metadata-Version: 1.0
Name: fnordstalk
Version: 0.0.5
Summary: A tool to save beanstalk stats to fnordmetric
Home-page: https://github.com/sholiday/fnordstalk
Author: Stephen Holiday
Author-email: stephen.holiday@gmail.com
License: UNKNOWN
Platform: UNKNOWN
Classifier: Development Status :: 3 - Alpha
Classifier: Intended Audience :: Developers
Classifier: License :: OSI Approved :: Apache Software License
Classifier: Operating System :: MacOS :: MacOS X
Classifier: Operating System :: POSIX
Classifier: Operating System :: Unix
Classifier: Programming Language :: Python :: 2.6
Classifier: Programming Language :: Python :: 2.7
Classifier: Programming Language :: Python
Classifier: Topic :: System :: Monitoring
